{"name": "borough > 1.5", "children": [{"name": "borough > 3.5", "children": [{"name": "time > 17.5249996185", "children": [{"name": "33326 of Non Fatal, 9308 of Fatal"}, {"name": "93374 of Non Fatal, 19949 of Fatal"}]}, {"name": "time > 7.94166660309", "children": [{"name": "136543 of Non Fatal, 22186 of Fatal"}, {"name": "19509 of Non Fatal, 4320 of Fatal"}]}]}, {"name": "time > 17.5083332062", "children": [{"name": "time > 19.0750007629", "children": [{"name": "34267 of Non Fatal, 12215 of Fatal"}, {"name": "19579 of Non Fatal, 6134 of Fatal"}]}, {"name": "time > 7.99166679382", "children": [{"name": "128053 of Non Fatal, 29646 of Fatal"}, {"name": "24941 of Non Fatal, 7963 of Fatal"}]}]}]}